asaman/__init__.py
asaman-0.2.1.dist-info/entry_points.txt
asaman-0.2.1.dist-info/LICENSE
asaman-0.2.1.dist-info/WHEEL
asaman-0.2.1.dist-info/METADATA
asaman-0.2.1.dist-info/RECORD
