Metadata-Version: 2.1
Name: asaman
Version: 0.2.1
Summary: A tool to create reproducible wheels
Author-email: Kushal Das <mail@kushaldas.in>
Requires-Python: >=3.6
Classifier: License :: OSI Approved :: MIT License
Requires-Dist: wheel
Requires-Dist: build>=0.7.0
Requires-Dist: click
Requires-Dist: pep517
Requires-Dist: setuptools
Requires-Dist: pip-requirements-parser
Project-URL: Documentation, https://asaman.readthedocs.io/en/latest/
Project-URL: Source, https://github.com/kushaldas/asaman
